epicstuff/__init__.py
epicstuff/dict.py
epicstuff/dict.pyi
epicstuff/fix_import.py
epicstuff/permissify.py
epicstuff/progress.py
epicstuff/s.py
epicstuff/stuff.py
epicstuff/timer.py
epicstuff/trace.py
epicstuff/version.py
epicstuff-1.0.1.dist-info/licenses/LICENSE
epicstuff-1.0.1.dist-info/METADATA
epicstuff-1.0.1.dist-info/PKG-INFO.sbak
epicstuff-1.0.1.dist-info/WHEEL
epicstuff-1.0.1.dist-info/top_level.txt
epicstuff-1.0.1.dist-info/RECORD
