Metadata-Version: 2.4
Name: epicstuff
Version: 1.0.1
Summary: a few somewhat useful objects and functions
Author-email: EpicStuff <EpicStuff@users.noreply.github.com>
Project-URL: Homepage, https://github.com/EpicStuff/python-EpicStuff
Project-URL: Issues, https://github.com/EpicStuff/python-EpicStuff/issues
Project-URL: Source, https://github.com/EpicStuff/python-EpicStuff
Classifier: Operating System :: OS Independent
Classifier: Programming Language :: Python :: 3
Classifier: Programming Language :: Python :: 3.13
Requires-Python: >=3.13
License-File: LICENSE
Requires-Dist: rich
Dynamic: license-file
